LICENSE
MANIFEST.in
README.md
setup.py
bn256/__init__.py
bn256/constants.py
bn256/curve.py
bn256/g1.py
bn256/g2.py
bn256/gfp12.py
bn256/gfp2.py
bn256/gfp6.py
bn256/gt.py
bn256/optate.py
bn256/twist.py
bn256/utils.py
bn256.egg-info/PKG-INFO
bn256.egg-info/SOURCES.txt
bn256.egg-info/dependency_links.txt
bn256.egg-info/top_level.txt
tests/test_curve.py
tests/test_g1.py
tests/test_g2.py
tests/test_gfp12.py
tests/test_gfp2.py
tests/test_gfp6.py
tests/test_gt.py
tests/test_optate.py
tests/test_twist.py
tests/test_utils.py