Metadata-Version: 2.1
Name: bn256
Version: 0.1.1
Summary: python bn256
Home-page: https://github.com/hanzhichao/bn256.git
Author: Han Zhichao
Author-email: superhin@126.com
License: MIT License
Keywords: bn256,python-bn256,hibe
Classifier: Development Status :: 3 - Alpha
Classifier: Topic :: Software Development :: User Interfaces
Classifier: Programming Language :: Python
Classifier: Programming Language :: Python :: 3.6
Classifier: Programming Language :: Python :: 3.7
Classifier: Programming Language :: Python :: 3.8
Classifier: Programming Language :: Python :: 3.9
Classifier: Programming Language :: Python :: 3.10
License-File: LICENSE
